Metadata-Version: 2.1
Name: MouseInfo
Version: 0.1.1
Summary: An application to display XY position and RGB color information for the pixel currently under the mouse. Works on Python 2 and 3.
Home-page: https://github.com/asweigart/mouseinfo
Author: Al Sweigart
Author-email: al@inventwithpython.com
License: GPLv3+
Platform: UNKNOWN
Classifier: License :: OSI Approved :: GNU General Public License v3 or later (GPLv3+)
Classifier: Programming Language :: Python
Classifier: Programming Language :: Python :: 2
Classifier: Programming Language :: Python :: 2.7
Classifier: Programming Language :: Python :: 3
Classifier: Programming Language :: Python :: 3.2
Classifier: Programming Language :: Python :: 3.3
Classifier: Programming Language :: Python :: 3.4
Classifier: Programming Language :: Python :: 3.5
Classifier: Programming Language :: Python :: 3.6
Classifier: Programming Language :: Python :: 3.7
